<?xml version="1.0" encoding="UTF-8"?>
<magicdraw><package classType="Package" humanType="Paquet" icon="Barrière Sympact_files/icon_1350453764.jpg" id="_17_0_3_7d60262_1371496680789_481862_14413"><TO_DO humanName="A Faire" mode="standard,expert"/><ownedElement humanName="Elément avec Possesseur"><statemachine classType="StateMachine" humanType="Machine à Etat" icon="Barrière Sympact_files/icon_2013274351.jpg" name="Diagramme d'état" refid="_17_0_3_7d60262_1364413643209_645198_14192"/></ownedElement><packagedElement humanName="Elément Paqueté"><statemachine classType="StateMachine" humanType="Machine à Etat" icon="Barrière Sympact_files/icon_2013274351.jpg" name="Diagramme d'état" refid="_17_0_3_7d60262_1364413643209_645198_14192"/></packagedElement><namespace classType="Model" humanName="Espace de Nommage" humanType="Modèle" icon="Barrière Sympact_files/icon_594914355.jpg" name="Diagrammes" refid="eee_1045467100313_135436_1"/><nestingPackage classType="Model" humanName="Imbrication de Paquetage" humanType="Modèle" icon="Barrière Sympact_files/icon_594914355.jpg" name="Diagrammes" refid="eee_1045467100313_135436_1"/><member humanName="Membre"><statemachine classType="StateMachine" humanType="Machine à Etat" icon="Barrière Sympact_files/icon_2013274351.jpg" name="Diagramme d'état" refid="_17_0_3_7d60262_1364413643209_645198_14192"/></member><ownedMember humanName="Membre avec Possesseur"><statemachine classType="StateMachine" humanType="Machine à Etat" icon="Barrière Sympact_files/icon_2013274351.jpg" name="Diagramme d'état" refid="_17_0_3_7d60262_1364413643209_645198_14192"/></ownedMember><name humanName="Nom" mode="standard,expert">Diagrammes comportementaux</name><qualifiedName humanName="Nom Qualifié" mode="expert">Diagrammes comportementaux</qualifiedName><owningPackage classType="Model" humanName="Paquetage de Possession" humanType="Modèle" icon="Barrière Sympact_files/icon_594914355.jpg" name="Diagrammes" refid="eee_1045467100313_135436_1"/><owner classType="Model" humanName="Possesseur" humanType="Modèle" icon="Barrière Sympact_files/icon_594914355.jpg" mode="standard,expert" name="Diagrammes" refid="eee_1045467100313_135436_1"/><ownedType humanName="Type avec Possesseur"><statemachine classType="StateMachine" humanType="Machine à Etat" icon="Barrière Sympact_files/icon_2013274351.jpg" name="Diagramme d'état" refid="_17_0_3_7d60262_1364413643209_645198_14192"/></ownedType><URI humanName="URI" mode="standard,expert"/><visibility humanName="Visibilité">public</visibility></package></magicdraw>