<?xml version="1.0" encoding="UTF-8"?>
<magicdraw><instancespecification classType="InstanceSpecification" humanType="Spécification d'Instance" icon="Barrière Sympact_files/icon_867376681.jpg" id="_17_0_3_7d60262_1361950791146_328986_13087"><TO_DO humanName="A Faire" mode="standard,expert"/><classifier humanName="Classificateur" mode="standard,expert"><stereotype classType="Stereotype" humanType="Stéréotype" icon="Barrière Sympact_files/icon_1536163678.jpg" name="NestedConnectorEnd" refid="_11_5EAPbeta_be00301_1147431307463_773225_1455"/></classifier><ownedElement humanName="Elément avec Possesseur"><slot classType="Slot" humanType="Emplacement" icon="Barrière Sympact_files/icon_1098359621.jpg" refid="_17_0_3_652021b_1505223562317_324807_9327"/></ownedElement><stereotypedElement classType="ConnectorEnd" humanName="Elément Stéréotypé" humanType="Fin de Connecteur" icon="Barrière Sympact_files/icon_1919150213.jpg" refid="_17_0_3_7d60262_1361950791146_290854_13083"/><slot humanName="Emplacement"><slot classType="Slot" humanType="Emplacement" icon="Barrière Sympact_files/icon_1098359621.jpg" refid="_17_0_3_652021b_1505223562317_324807_9327"/></slot><name humanName="Nom" mode="standard,expert"/><qualifiedName humanName="Nom Qualifié" mode="expert">Diagrammes structurels::Blocs::Chaîne d'information::::</qualifiedName><owner classType="ConnectorEnd" humanName="Possesseur" humanType="Fin de Connecteur" icon="Barrière Sympact_files/icon_1919150213.jpg" mode="standard,expert" refid="_17_0_3_7d60262_1361950791146_290854_13083"/><visibility humanName="Visibilité">public</visibility></instancespecification></magicdraw>